probability_distro/Binomialdistribution.py
probability_distro/Gaussiandistribution.py
probability_distro/Generaldistribution.py
probability_distro/__init__.py
probability_distro-0.1.3.dist-info/METADATA
probability_distro-0.1.3.dist-info/WHEEL
probability_distro-0.1.3.dist-info/top_level.txt
probability_distro-0.1.3.dist-info/RECORD
