Metadata-Version: 2.1
Name: probability-distro
Version: 0.1.3
Summary: Gaussian and Binomal distributions
Home-page: https://github.com/vamsigutha/probability-distro
Author: Vamsi Krishna Gutha
Author-email: vamsigutha27@gmail.com
License: UNKNOWN
Platform: UNKNOWN
